{
  "categories": [
    {
      "id": "cat1",
      "name": "Groceries",
      "description": "All food-related purchases",
      "imageUrl": ""
    },
    {
      "id": "cat2",
      "name": "Transport",
      "description": "Expenses on public and private transport",
      "imageUrl": ""
    },
    {
      "id": "cat3",
      "name": "Dining",
      "description": "Restaurant and cafe expenses",
      "imageUrl": ""
    },
    {
      "id": "cat4",
      "name": "Education",
      "description": "Expenses on books, courses, and other educational materials",
      "imageUrl": ""
    },
    {
      "id": "cat5",
      "name": "Health",
      "description": "Medical expenses and health supplements",
      "imageUrl": ""
    }
  ],
  "expenses": [
    {
      "id": "exp1",
      "userId": "user1",
      "amount": 150.0,
      "categoryId": "cat1",
      "date": "2024-02-14",
      "description": "Grocery Shopping"
    },
    {
      "id": "exp2",
      "userId": "user2",
      "amount": 75.0,
      "categoryId": "cat2",
      "date": "2024-02-15",
      "description": "Public Transport"
    },
    {
      "id": "exp3",
      "userId": "user1",
      "amount": 200.0,
      "categoryId": "cat3",
      "date": "2024-02-16",
      "description": "Restaurant"
    },
    {
      "id": "exp4",
      "userId": "user2",
      "amount": 50.0,
      "categoryId": "cat4",
      "date": "2024-02-17",
      "description": "Books"
    },
    {
      "id": "exp5",
      "userId": "user1",
      "amount": 120.0,
      "categoryId": "cat5",
      "date": "2024-02-18",
      "description": "Healthcare"
    }
  ],
  "incomes": [
    {
      "id": "inc1",
      "userId": "user1",
      "amount": 2000.0,
      "description": "Salary",
      "date": "2024-02-07"
    },
    {
      "id": "inc2",
      "userId": "user2",
      "amount": 1500.0,
      "description": "Freelancing",
      "date": "2024-02-14"
    },
    {
      "id": "inc3",
      "userId": "user1",
      "amount": 500.0,
      "description": "Investment Returns",
      "date": "2024-02-21"
    },
    {
      "id": "inc4",
      "userId": "user2",
      "amount": 750.0,
      "description": "Gift",
      "date": "2024-02-28"
    },
    {
      "id": "inc5",
      "userId": "user1",
      "amount": 250.0,
      "description": "Lottery Winnings",
      "date": "2024-03-07"
    }
  ],
  "budgets": [
    {
      "id": "bud1",
      "categoryId": "cat1",
      "totalAmount": 500.0,
      "startDate": "2024-02-01",
      "endDate": "2024-02-28"
    },
    {
      "id": "bud2",
      "categoryId": "cat2",
      "totalAmount": 300.0,
      "startDate": "2024-03-01",
      "endDate": "2024-03-31"
    },
    {
      "id": "bud3",
      "categoryId": "cat3",
      "totalAmount": 400.0,
      "startDate": "2024-04-01",
      "endDate": "2024-04-30"
    },
    {
      "id": "bud4",
      "categoryId": "cat4",
      "totalAmount": 250.0,
      "startDate": "2024-05-01",
      "endDate": "2024-05-31"
    },
    {
      "id": "bud5",
      "categoryId": "cat5",
      "totalAmount": 600.0,
      "startDate": "2024-06-01",
      "endDate": "2024-06-30"
    }
  ]
}
